<?xml version="1.0" encoding="UTF-8"?>
<simpleviewerGallery maxImageWidth="480" maxImageHeight="480" textColor="0xFFFFFF" frameColor="0xFFFFFF" frameWidth="5" stagePadding="20" thumbnailColumns="3" thumbnailRows="5" navPosition="left" title="" enableRightClickOpen="false" backgroundImagePath="" imagePath="images/" thumbPath="thumb/">
<image>
<filename>DSC_8965.jpg</filename>
<caption></caption>
</image>
<image>
<filename>DSC_8980.jpg</filename>
<caption></caption>
</image>
<image>
<filename>DSC_8983.jpg</filename>
<caption></caption>
</image>
<image>
<filename>DSC_9001.jpg</filename>
<caption></caption>
</image>
<image>
<filename>DSC_9005.jpg</filename>
<caption></caption>
</image>
<image>
<filename>DSC_9007.jpg</filename>
<caption></caption>
</image>
<image>
<filename>DSC_9016.jpg</filename>
<caption></caption>
</image>
<image>
<filename>DSC_9024.jpg</filename>
<caption></caption>
</image>
<image>
<filename>DSC_9028.jpg</filename>
<caption></caption>
</image>
<image>
<filename>DSC_9043.jpg</filename>
<caption></caption>
</image>
<image>
<filename>DSC_9046.jpg</filename>
<caption></caption>
</image>
<image>
<filename>DSC_9052.jpg</filename>
<caption></caption>
</image>
<image>
<filename>DSC_9054.jpg</filename>
<caption></caption>
</image>
<image>
<filename>DSC_9062.jpg</filename>
<caption></caption>
</image>
<image>
<filename>DSC_9073.jpg</filename>
<caption></caption>
</image>
</simpleviewerGallery>
